httpretty/__init__.py
httpretty/compat.py
httpretty/core.py
httpretty/errors.py
httpretty/http.py
httpretty/utils.py
httpretty/version.py
fauxhttp-0.1.0.dist-info/COPYING
fauxhttp-0.1.0.dist-info/METADATA
fauxhttp-0.1.0.dist-info/WHEEL
fauxhttp-0.1.0.dist-info/top_level.txt
fauxhttp-0.1.0.dist-info/RECORD
