Metadata-Version: 2.1
Name: fauxhttp
Version: 0.1.0
Summary: HTTP client mock for Python
Home-page: https://httpretty.readthedocs.io/en/latest/
Author: Gabriel Falcao
Author-email: gabriel@nacaolivre.org
License: MIT
Project-URL: Documentation, https://httpretty.readthedocs.io/en/latest/
Project-URL: Source Code, https://github.com/Secrus/fauxhttp
Project-URL: Issue Tracker, https://github.com/Secrus/fauxhttp/issues
Classifier: Development Status :: 5 - Production/Stable
Classifier: Intended Audience :: Developers
Classifier: License :: OSI Approved :: MIT License
Classifier: Programming Language :: Python :: 3
Classifier: Programming Language :: Python :: 3.6
Classifier: Programming Language :: Python :: 3.7
Classifier: Programming Language :: Python :: 3.8
Classifier: Programming Language :: Python :: 3.9
Classifier: Programming Language :: Python
Classifier: Topic :: Internet :: WWW/HTTP
Classifier: Topic :: Software Development :: Testing
Requires-Python: >=3
License-File: COPYING
